web/__init__.py
web/components/__init__.py
web/components/api.py
web/components/code.py
web/components/html.py
web/components/ipynb.py
web/components/md.py
web/components/raw.py
web/core/__init__.py
web/core/api.py
web/core/app.py
web/core/block.py
web/impl/__init__.py
web/impl/lxml_code.py
web/impl/lxml_components.py
web/impl/lxml_ipynb.py
web/impl/lxml_md.py
web/impl/lxml_raw.py
web/impl/lxml_toolkit_object.py
enaml_web-0.10.2.dist-info/LICENSE.txt
enaml_web-0.10.2.dist-info/METADATA
enaml_web-0.10.2.dist-info/WHEEL
enaml_web-0.10.2.dist-info/top_level.txt
enaml_web-0.10.2.dist-info/RECORD
