Metadata-Version: 2.1
Name: enaml-web
Version: 0.10.2
Summary: Web component toolkit for Enaml
Home-page: https://github.com/codelv/enaml-web
Author: CodeLV
Author-email: frmdstryr@gmail.com
License: MIT
Platform: UNKNOWN
Requires: enaml
Requires-Dist: enaml (>=0.9.8)
Requires-Dist: lxml (>=3.4.0)
